gph/__init__.py
gph/_version.py
gph/modules/gph_collapser.cp310-win_amd64.pyd
gph/modules/gph_ripser.cp310-win_amd64.pyd
gph/modules/gph_ripser_coeff.cp310-win_amd64.pyd
gph/python/__init__.py
gph/python/ripser_interface.py
gph/python/test/__init__.py
gph/python/test/test_collapser.py
gph/python/test/test_ripser.py
gph/python/test/test_wrp.py
giotto_ph-0.2.4.dist-info/LICENSE
giotto_ph-0.2.4.dist-info/METADATA
giotto_ph-0.2.4.dist-info/WHEEL
giotto_ph-0.2.4.dist-info/top_level.txt
giotto_ph-0.2.4.dist-info/RECORD
